docs_mcp/__init__.py
docs_mcp/__main__.py
docs_mcp/config.py
docs_mcp/server.py
docs_mcp/web.py
docs_mcp/handlers/__init__.py
docs_mcp/handlers/resources.py
docs_mcp/handlers/tools.py
docs_mcp/models/__init__.py
docs_mcp/models/document.py
docs_mcp/models/navigation.py
docs_mcp/models/openapi.py
docs_mcp/security/__init__.py
docs_mcp/security/path_validator.py
docs_mcp/security/sanitizer.py
docs_mcp/services/__init__.py
docs_mcp/services/cache.py
docs_mcp/services/hierarchy.py
docs_mcp/services/markdown.py
docs_mcp/services/search.py
docs_mcp/services/vector.py
docs_mcp/static/app.js
docs_mcp/static/index.html
docs_mcp/utils/__init__.py
docs_mcp/utils/logger.py
your_docs_mcp-0.0.5.dist-info/licenses/LICENSE
your_docs_mcp-0.0.5.dist-info/METADATA
your_docs_mcp-0.0.5.dist-info/WHEEL
your_docs_mcp-0.0.5.dist-info/entry_points.txt
your_docs_mcp-0.0.5.dist-info/top_level.txt
your_docs_mcp-0.0.5.dist-info/RECORD
