Metadata-Version: 2.4
Name: your-docs-mcp
Version: 0.0.5
Summary: Model Context Protocol server for hierarchical documentation navigation with markdown and OpenAPI support
Author: MCP Contributors
License: MIT
Project-URL: Homepage, https://github.com/esola-thomas/Markdown-MCP
Project-URL: Repository, https://github.com/esola-thomas/Markdown-MCP
Keywords: mcp,documentation,ai,openapi,markdown
Classifier: Development Status :: 3 - Alpha
Classifier: Intended Audience :: Developers
Classifier: License :: OSI Approved :: MIT License
Classifier: Programming Language :: Python :: 3
Classifier: Programming Language :: Python :: 3.11
Classifier: Programming Language :: Python :: 3.12
Requires-Python: >=3.10
License-File: LICENSE
Requires-Dist: mcp>=0.1.0
Requires-Dist: pyyaml>=6.0
Requires-Dist: pydantic>=2.0
Requires-Dist: pydantic-settings>=2.0
Requires-Dist: openapi-spec-validator>=0.7.0
Requires-Dist: prance>=23.6.21.0
Requires-Dist: watchdog>=3.0.0
Requires-Dist: fastapi>=0.104.0
Requires-Dist: uvicorn>=0.24.0
Provides-Extra: vector
Requires-Dist: chromadb>=0.4.0; extra == "vector"
Requires-Dist: sentence-transformers>=2.2.2; extra == "vector"
Provides-Extra: vector-gpu
Requires-Dist: chromadb>=0.4.0; extra == "vector-gpu"
Requires-Dist: sentence-transformers>=2.2.2; extra == "vector-gpu"
Provides-Extra: pdf
Requires-Dist: Pillow>=9.0.0; extra == "pdf"
Provides-Extra: dev
Requires-Dist: pytest>=7.4.0; extra == "dev"
Requires-Dist: pytest-asyncio>=0.21.0; extra == "dev"
Requires-Dist: httpx>=0.25.0; extra == "dev"
Requires-Dist: pytest-mock>=3.11.0; extra == "dev"
Requires-Dist: pytest-cov>=4.1.0; extra == "dev"
Requires-Dist: ruff>=0.1.0; extra == "dev"
Requires-Dist: mypy>=1.5.0; extra == "dev"
Requires-Dist: types-PyYAML; extra == "dev"
Requires-Dist: python-dotenv>=1.0.0; extra == "dev"
Dynamic: license-file
